modape/_whittaker.pyx
modape/utils.py
modape/whittaker.cpython-36m-x86_64-linux-gnu.so
modape/constants.py
modape/__init__.py
modape/exceptions.py
modape/scripts/csv_smooth.py
modape/scripts/modis_window.py
modape/scripts/__init__.py
modape/scripts/modis_smooth.py
modape/scripts/modis_collect.py
modape/scripts/modis_download.py
modape/scripts/modis_info.py
modape/modis/download.py
modape/modis/__init__.py
modape/modis/io.py
modape/modis/collect.py
modape/modis/window.py
modape/modis/smooth.py
modape/data/cmr_api_response.pkl
modape/data/MXD_dates.pkl
modape/data/MXD_testdata.pkl
modape/data/hdf.xml
modape-1.0.3.dist-info/LICENSE
modape-1.0.3.dist-info/entry_points.txt
modape-1.0.3.dist-info/WHEEL
modape-1.0.3.dist-info/top_level.txt
modape-1.0.3.dist-info/RECORD
modape-1.0.3.dist-info/METADATA
_version/version_info.py
_version/__init__.py
